cz_git_universal_jira_conventional
