Metadata-Version: 2.1
Name: cz-git-universal-jira-conventional
Version: 1.2.0
Summary: Extend the commitizen tools to create conventional commits and README that link to Jira and Git Project.
Home-page: https://github.com/ngoldack/cz-git-universal-jira-conventional
Author: Nicolas Goldack
Author-email: nicolas-goldack@live.de
License: MIT
Platform: UNKNOWN
License-File: LICENSE
